{
    "book": "Isaiah",
    "chapter": "Chapter 21",
    "verses": [
        {
            "name": "Isaiah 21:8",
            "text": "And he cried, A lion: My lord, I stand continually upon the watchtower in the daytime, and I am set in my ward whole nights:"
        },
        {
            "name": "Isaiah 21:9",
            "text": "And, behold, here cometh a chariot of men, with a couple of horsemen. And he answered and said, Babylon is fallen, is fallen; and all the graven images of her gods he hath broken unto the ground."
        },
        {
            "name": "Isaiah 21:10",
            "text": "O my threshing, and the corn of my floor: that which I have heard of the Lord of hosts, the God of Israel, have I declared unto you."
        }
    ],
    "tone": "lamenting"
}