{
    "book": "1 Chronicles",
    "chapter": "Chapter 4",
    "verses": [
        {
            "name": "1 Chronicles 4:10",
            "text": "And Jabez called on the God of Israel, saying, Oh that thou wouldest bless me indeed, and enlarge my coast, and that thine hand might be with me, and that thou wouldest keep me from evil, that it may not grieve me! And God granted him that which he requested."
        },
        {
            "name": "1 Chronicles 4:11",
            "text": "And Chelub the brother of Shuah begat Mehir, which was the father of Eshton."
        },
        {
            "name": "1 Chronicles 4:12",
            "text": "And Eshton begat Beth\u2013rapha, and Paseah, and Tehinnah the father of Ir\u2013nahash. These are the men of Rechah."
        },
        {
            "name": "1 Chronicles 4:13",
            "text": "And the sons of Kenaz; Othniel, and Seraiah: and the sons of Othniel; Hathath."
        }
    ],
    "tone": "praising"
}