{
    "book": "Ezekiel",
    "chapter": "Chapter 28",
    "verses": [
        {
            "name": "Ezekiel 28:24",
            "text": "And there shall be no more a pricking brier unto the house of Israel, nor any grieving thorn of all that are round about them, that despised them; and they shall know that I am the Lord God."
        },
        {
            "name": "Ezekiel 28:25",
            "text": "Thus saith the Lord God; When I shall have gathered the house of Israel from the people among whom they are scattered, and shall be sanctified in them in the sight of the heathen, then shall they dwell in their land that I have given to my servant Jacob."
        }
    ],
    "tone": "neutral"
}