{
    "book": "2 Chronicles",
    "chapter": "Chapter 20",
    "verses": [
        {
            "name": "2 Chronicles 20:13",
            "text": "And all Judah stood before the Lord, with their little ones, their wives, and their children."
        },
        {
            "name": "2 Chronicles 20:14",
            "text": "Then upon Jahaziel the son of Zechariah, the son of Benaiah, the son of Jeiel, the son of Mattaniah, a Levite of the sons of Asaph, came the Spirit of the Lord in the midst of the congregation;"
        },
        {
            "name": "2 Chronicles 20:15",
            "text": "And he said, Hearken ye, all Judah, and ye inhabitants of Jerusalem, and thou king Jehoshaphat, Thus saith the Lord unto you, Be not afraid nor dismayed by reason of this great multitude; for the battle is not yours, but God\u2019s."
        }
    ],
    "tone": "neutral"
}