{
    "book": "Judges",
    "chapter": "Chapter 21",
    "verses": [
        {
            "name": "Judges 21:10",
            "text": "And the congregation sent thither twelve thousand men of the valiantest, and commanded them, saying, Go and smite the inhabitants of Jabesh\u2013gilead with the edge of the sword, with the women and the children."
        },
        {
            "name": "Judges 21:11",
            "text": "And this is the thing that ye shall do, Ye shall utterly destroy every male, and every woman that hath lain by man."
        },
        {
            "name": "Judges 21:12",
            "text": "And they found among the inhabitants of Jabesh\u2013gilead four hundred young virgins, that had known no man by lying with any male: and they brought them unto the camp to Shiloh, which is in the land of Canaan."
        }
    ],
    "tone": "neutral"
}