{
    "book": "Proverbs",
    "chapter": "Chapter 24",
    "verses": [
        {
            "name": "Proverbs 24:29",
            "text": "Say not, I will do so to him as he hath done to me: I will render to the man according to his work."
        },
        {
            "name": "Proverbs 24:30",
            "text": "I went by the field of the slothful, and by the vineyard of the man void of understanding;"
        },
        {
            "name": "Proverbs 24:31",
            "text": "And, lo, it was all grown over with thorns, and nettles had covered the face thereof, and the stone wall thereof was broken down."
        },
        {
            "name": "Proverbs 24:32",
            "text": "Then I saw, and considered it well: I looked upon it, and received instruction."
        },
        {
            "name": "Proverbs 24:33",
            "text": "Yet a little sleep, a little slumber, a little folding of the hands to sleep:"
        }
    ],
    "tone": "neutral"
}