{
    "book": "Job",
    "chapter": "Chapter 18",
    "verses": [
        {
            "name": "Job 18:7",
            "text": "The steps of his strength shall be straitened, and his own counsel shall cast him down."
        },
        {
            "name": "Job 18:8",
            "text": "For he is cast into a net by his own feet, and he walketh upon a snare."
        },
        {
            "name": "Job 18:9",
            "text": "The gin shall take him by the heel, and the robber shall prevail against him."
        },
        {
            "name": "Job 18:10",
            "text": "The snare is laid for him in the ground, and a trap for him in the way."
        },
        {
            "name": "Job 18:11",
            "text": "Terrors shall make him afraid on every side, and shall drive him to his feet."
        },
        {
            "name": "Job 18:12",
            "text": "His strength shall be hungerbitten, and destruction shall be ready at his side."
        }
    ],
    "tone": "lamenting"
}