{
    "book": "2 Chronicles",
    "chapter": "Chapter 3",
    "verses": [
        {
            "name": "2 Chronicles 3:7",
            "text": "He overlaid also the house, the beams, the posts, and the walls thereof, and the doors thereof, with gold; and graved cherubims on the walls."
        },
        {
            "name": "2 Chronicles 3:8",
            "text": "And he made the most holy house, the length whereof was according to the breadth of the house, twenty cubits, and the breadth thereof twenty cubits: and he overlaid it with fine gold, amounting to six hundred talents."
        },
        {
            "name": "2 Chronicles 3:9",
            "text": "And the weight of the nails was fifty shekels of gold. And he overlaid the upper chambers with gold."
        },
        {
            "name": "2 Chronicles 3:10",
            "text": "And in the most holy house he made two cherubims of image work, and overlaid them with gold."
        }
    ],
    "tone": "instructional"
}