{
    "book": "Proverbs",
    "chapter": "Chapter 12",
    "verses": [
        {
            "name": "Proverbs 12:11",
            "text": "He that tilleth his land shall be satisfied with bread: but he that followeth vain persons is void of understanding."
        },
        {
            "name": "Proverbs 12:12",
            "text": "The wicked desireth the net of evil men: but the root of the righteous yieldeth fruit."
        },
        {
            "name": "Proverbs 12:13",
            "text": "The wicked is snared by the transgression of his lips: but the just shall come out of trouble."
        },
        {
            "name": "Proverbs 12:14",
            "text": "A man shall be satisfied with good by the fruit of his mouth: and the recompence of a man\u2019s hands shall be rendered unto him."
        },
        {
            "name": "Proverbs 12:15",
            "text": "The way of a fool is right in his own eyes: but he that hearkeneth unto counsel is wise."
        }
    ],
    "tone": "instructional"
}