{
    "book": "Genesis",
    "chapter": "Chapter 49",
    "verses": [
        {
            "name": "Genesis 49:29",
            "text": "And he charged them, and said unto them, I am to be gathered unto my people: bury me with my fathers in the cave that is in the field of Ephron the Hittite,"
        },
        {
            "name": "Genesis 49:30",
            "text": "In the cave that is in the field of Machpelah, which is before Mamre, in the land of Canaan, which Abraham bought with the field of Ephron the Hittite for a possession of a buryingplace."
        },
        {
            "name": "Genesis 49:31",
            "text": "There they buried Abraham and Sarah his wife; there they buried Isaac and Rebekah his wife; and there I buried Leah."
        }
    ],
    "tone": "neutral"
}