{
    "book": "Psalms",
    "chapter": "Chapter 84",
    "verses": [
        {
            "name": "Psalms 84:6",
            "text": "Who passing through the valley of Baca make it a well; the rain also filleth the pools."
        },
        {
            "name": "Psalms 84:7",
            "text": "They go from strength to strength, every one of them in Zion appeareth before God."
        },
        {
            "name": "Psalms 84:8",
            "text": "O Lord God of hosts, hear my prayer: give ear, O God of Jacob. Selah."
        },
        {
            "name": "Psalms 84:9",
            "text": "Behold, O God our shield, and look upon the face of thine anointed."
        },
        {
            "name": "Psalms 84:10",
            "text": "For a day in thy courts is better than a thousand. I had rather be a doorkeeper in the house of my God, than to dwell in the tents of wickedness."
        }
    ],
    "tone": "neutral"
}