{
    "book": "Zechariah",
    "chapter": "Chapter 5",
    "verses": [
        {
            "name": "Zechariah 5:1",
            "text": "Then I turned, and lifted up mine eyes, and looked, and behold a flying roll."
        },
        {
            "name": "Zechariah 5:2",
            "text": "And he said unto me, What seest thou? And I answered, I see a flying roll; the length thereof is twenty cubits, and the breadth thereof ten cubits."
        },
        {
            "name": "Zechariah 5:3",
            "text": "Then said he unto me, This is the curse that goeth forth over the face of the whole earth: for every one that stealeth shall be cut off as on this side according to it; and every one that sweareth shall be cut off as on that side according to it."
        }
    ],
    "tone": "neutral"
}