{
    "book": "Matthew",
    "chapter": "Chapter 15",
    "verses": [
        {
            "name": "Matthew 15:32",
            "text": "Then Jesus called his disciples unto him, and said, I have compassion on the multitude, because they continue with me now three days, and have nothing to eat: and I will not send them away fasting, lest they faint in the way."
        },
        {
            "name": "Matthew 15:33",
            "text": "And his disciples say unto him, Whence should we have so much bread in the wilderness, as to fill so great a multitude?"
        },
        {
            "name": "Matthew 15:34",
            "text": "And Jesus saith unto them, How many loaves have ye? And they said, Seven, and a few little fishes."
        },
        {
            "name": "Matthew 15:35",
            "text": "And he commanded the multitude to sit down on the ground."
        }
    ],
    "tone": "hopeful"
}