{
    "book": "2 Chronicles",
    "chapter": "Chapter 16",
    "verses": [
        {
            "name": "2 Chronicles 16:1",
            "text": "In the six and thirtieth year of the reign of Asa Baasha king of Israel came up against Judah, and built Ramah, to the intent that he might let none go out or come in to Asa king of Judah."
        },
        {
            "name": "2 Chronicles 16:2",
            "text": "Then Asa brought out silver and gold out of the treasures of the house of the Lord and of the king\u2019s house, and sent to Ben\u2013hadad king of Syria, that dwelt at Damascus, saying,"
        }
    ],
    "tone": "neutral"
}