{
    "book": "Job",
    "chapter": "Chapter 11",
    "verses": [
        {
            "name": "Job 11:7",
            "text": "Canst thou by searching find out God? canst thou find out the Almighty unto perfection?"
        },
        {
            "name": "Job 11:8",
            "text": "It is as high as heaven; what canst thou do? deeper than hell; what canst thou know?"
        },
        {
            "name": "Job 11:9",
            "text": "The measure thereof is longer than the earth, and broader than the sea."
        },
        {
            "name": "Job 11:10",
            "text": "If he cut off, and shut up, or gather together, then who can hinder him?"
        },
        {
            "name": "Job 11:11",
            "text": "For he knoweth vain men: he seeth wickedness also; will he not then consider it?"
        },
        {
            "name": "Job 11:12",
            "text": "For vain man would be wise, though man be born like a wild ass\u2019s colt."
        }
    ],
    "tone": "praising"
}