{
    "book": "Psalms",
    "chapter": "Chapter 94",
    "verses": [
        {
            "name": "Psalms 94:1",
            "text": "O Lord God, to whom vengeance belongeth; O God, to whom vengeance belongeth, shew thyself."
        },
        {
            "name": "Psalms 94:2",
            "text": "Lift up thyself, thou judge of the earth: render a reward to the proud."
        },
        {
            "name": "Psalms 94:3",
            "text": "Lord, how long shall the wicked, how long shall the wicked triumph?"
        },
        {
            "name": "Psalms 94:4",
            "text": "How long shall they utter and speak hard things? and all the workers of iniquity boast themselves?"
        },
        {
            "name": "Psalms 94:5",
            "text": "They break in pieces thy people, O Lord, and afflict thine heritage."
        },
        {
            "name": "Psalms 94:6",
            "text": "They slay the widow and the stranger, and murder the fatherless."
        },
        {
            "name": "Psalms 94:7",
            "text": "Yet they say, The Lord shall not see, neither shall the God of Jacob regard it."
        }
    ],
    "tone": "hopeful"
}