{
    "book": "2 Chronicles",
    "chapter": "Chapter 16",
    "verses": [
        {
            "name": "2 Chronicles 16:8",
            "text": "Were not the Ethiopians and the Lubims a huge host, with very many chariots and horsemen? yet, because thou didst rely on the Lord, he delivered them into thine hand."
        },
        {
            "name": "2 Chronicles 16:9",
            "text": "For the eyes of the Lord run to and fro throughout the whole earth, to shew himself strong in the behalf of them whose heart is perfect toward him. Herein thou hast done foolishly: therefore from henceforth thou shalt have wars."
        }
    ],
    "tone": "hopeful"
}