{
    "book": "Exodus",
    "chapter": "Chapter 34",
    "verses": [
        {
            "name": "Exodus 34:16",
            "text": "And thou take of their daughters unto thy sons, and their daughters go a whoring after their gods, and make thy sons go a whoring after their gods."
        },
        {
            "name": "Exodus 34:17",
            "text": "Thou shalt make thee no molten gods."
        },
        {
            "name": "Exodus 34:18",
            "text": "The feast of unleavened bread shalt thou keep. Seven days thou shalt eat unleavened bread, as I commanded thee, in the time of the month Abib: for in the month Abib thou camest out from Egypt."
        },
        {
            "name": "Exodus 34:19",
            "text": "All that openeth the matrix is mine; and every firstling among thy cattle, whether ox or sheep, that is male."
        }
    ],
    "tone": "lamenting"
}