{
    "book": "Deuteronomy",
    "chapter": "Chapter 33",
    "verses": [
        {
            "name": "Deuteronomy 33:17",
            "text": "His glory is like the firstling of his bullock, and his horns are like the horns of unicorns: with them he shall push the people together to the ends of the earth: and they are the ten thousands of Ephraim, and they are the thousands of Manasseh."
        },
        {
            "name": "Deuteronomy 33:18",
            "text": "And of Zebulun he said, Rejoice, Zebulun, in thy going out; and, Issachar, in thy tents."
        },
        {
            "name": "Deuteronomy 33:19",
            "text": "They shall call the people unto the mountain; there they shall offer sacrifices of righteousness: for they shall suck of the abundance of the seas, and of treasures hid in the sand."
        }
    ],
    "tone": "neutral"
}