{
    "book": "Song of Solomon",
    "chapter": "Chapter 3",
    "verses": [
        {
            "name": "Song of Songs 3:4",
            "text": "It was but a little that I passed from them, but I found him whom my soul loveth: I held him, and would not let him go, until I had brought him into my mother\u2019s house, and into the chamber of her that conceived me."
        },
        {
            "name": "Song of Songs 3:5",
            "text": "I charge you, O ye daughters of Jerusalem, by the roes, and by the hinds of the field, that ye stir not up, nor awake my love, till he please."
        },
        {
            "name": "Song of Songs 3:6",
            "text": "Who is this that cometh out of the wilderness like pillars of smoke, perfumed with myrrh and frankincense, with all powders of the merchant?"
        }
    ],
    "tone": "neutral"
}