{
    "book": "Exodus",
    "chapter": "Chapter 39",
    "verses": [
        {
            "name": "Exodus 39:23",
            "text": "And there was an hole in the midst of the robe, as the hole of an habergeon, with a band round about the hole, that it should not rend."
        },
        {
            "name": "Exodus 39:24",
            "text": "And they made upon the hems of the robe pomegranates of blue, and purple, and scarlet, and twined linen."
        },
        {
            "name": "Exodus 39:25",
            "text": "And they made bells of pure gold, and put the bells between the pomegranates upon the hem of the robe, round about between the pomegranates;"
        },
        {
            "name": "Exodus 39:26",
            "text": "A bell and a pomegranate, a bell and a pomegranate, round about the hem of the robe to minister in; as the Lord commanded Moses."
        }
    ],
    "tone": "neutral"
}