{
    "book": "Numbers",
    "chapter": "Chapter 7",
    "verses": [
        {
            "name": "Numbers 7:71",
            "text": "And for a sacrifice of peace offerings, two oxen, five rams, five he goats, five lambs of the first year: this was the offering of Ahiezer the son of Ammishaddai."
        },
        {
            "name": "Numbers 7:72",
            "text": "On the eleventh day Pagiel the son of Ocran, prince of the children of Asher, offered:"
        },
        {
            "name": "Numbers 7:73",
            "text": "His offering was one silver charger, the weight whereof was an hundred and thirty shekels, one silver bowl of seventy shekels, after the shekel of the sanctuary; both of them full of fine flour mingled with oil for a meat offering:"
        },
        {
            "name": "Numbers 7:74",
            "text": "One golden spoon of ten shekels, full of incense:"
        }
    ],
    "tone": "hopeful"
}