{
    "book": "Judges",
    "chapter": "Chapter 9",
    "verses": [
        {
            "name": "Judges 9:1",
            "text": "And Abimelech the son of Jerubbaal went to Shechem unto his mother\u2019s brethren, and communed with them, and with all the family of the house of his mother\u2019s father, saying,"
        },
        {
            "name": "Judges 9:2",
            "text": "Speak, I pray you, in the ears of all the men of Shechem, Whether is better for you, either that all the sons of Jerubbaal, which are threescore and ten persons, reign over you, or that one reign over you? remember also that I am your bone and your flesh."
        }
    ],
    "tone": "neutral"
}