{
    "book": "Deuteronomy",
    "chapter": "Chapter 8",
    "verses": [
        {
            "name": "Deuteronomy 8:3",
            "text": "And he humbled thee, and suffered thee to hunger, and fed thee with manna, which thou knewest not, neither did thy fathers know; that he might make thee know that man doth not live by bread only, but by every word that proceedeth out of the mouth of the Lord doth man live."
        },
        {
            "name": "Deuteronomy 8:4",
            "text": "Thy raiment waxed not old upon thee, neither did thy foot swell, these forty years."
        },
        {
            "name": "Deuteronomy 8:5",
            "text": "Thou shalt also consider in thine heart, that, as a man chasteneth his son, so the Lord thy God chasteneth thee."
        }
    ],
    "tone": "neutral"
}