{
    "book": "Isaiah",
    "chapter": "Chapter 35",
    "verses": [
        {
            "name": "Isaiah 35:1",
            "text": "The wilderness and the solitary place shall be glad for them; and the desert shall rejoice, and blossom as the rose."
        },
        {
            "name": "Isaiah 35:2",
            "text": "It shall blossom abundantly, and rejoice even with joy and singing: the glory of Lebanon shall be given unto it, the excellency of Carmel and Sharon, they shall see the glory of the Lord, and the excellency of our God."
        },
        {
            "name": "Isaiah 35:3",
            "text": "Strengthen ye the weak hands, and confirm the feeble knees."
        }
    ],
    "tone": "hopeful"
}