{
    "book": "Joshua",
    "chapter": "Chapter 17",
    "verses": [
        {
            "name": "Joshua 17:5",
            "text": "And there fell ten portions to Manasseh, beside the land of Gilead and Bashan, which were on the other side Jordan;"
        },
        {
            "name": "Joshua 17:6",
            "text": "Because the daughters of Manasseh had an inheritance among his sons: and the rest of Manasseh\u2019s sons had the land of Gilead."
        },
        {
            "name": "Joshua 17:7",
            "text": "And the coast of Manasseh was from Asher to Michmethah, that lieth before Shechem; and the border went along on the right hand unto the inhabitants of En\u2013tappuah."
        },
        {
            "name": "Joshua 17:8",
            "text": "Now Manasseh had the land of Tappuah: but Tappuah on the border of Manasseh belonged to the children of Ephraim;"
        }
    ],
    "tone": "neutral"
}