{
    "book": "Habakkuk",
    "chapter": "Chapter 3",
    "verses": [
        {
            "name": "Habakkuk 3:9",
            "text": "Thy bow was made quite naked, according to the oaths of the tribes, even thy word. Selah. Thou didst cleave the earth with rivers."
        },
        {
            "name": "Habakkuk 3:10",
            "text": "The mountains saw thee, and they trembled: the overflowing of the water passed by: the deep uttered his voice, and lifted up his hands on high."
        },
        {
            "name": "Habakkuk 3:11",
            "text": "The sun and moon stood still in their habitation: at the light of thine arrows they went, and at the shining of thy glittering spear."
        },
        {
            "name": "Habakkuk 3:12",
            "text": "Thou didst march through the land in indignation, thou didst thresh the heathen in anger."
        }
    ],
    "tone": "neutral"
}