{
    "book": "1 Kings",
    "chapter": "Chapter 19",
    "verses": [
        {
            "name": "1 Kings 19:4",
            "text": "But he himself went a day\u2019s journey into the wilderness, and came and sat down under a juniper tree: and he requested for himself that he might die; and said, It is enough; now, O Lord, take away my life; for I am not better than my fathers."
        },
        {
            "name": "1 Kings 19:5",
            "text": "And as he lay and slept under a juniper tree, behold, then an angel touched him, and said unto him, Arise and eat."
        }
    ],
    "tone": "neutral"
}